tlsx/extractor.py
tlsx-1.0.3.dist-info/DESCRIPTION.rst
tlsx-1.0.3.dist-info/METADATA
tlsx-1.0.3.dist-info/RECORD
tlsx-1.0.3.dist-info/WHEEL
tlsx-1.0.3.dist-info/entry_points.txt
tlsx-1.0.3.dist-info/metadata.json
tlsx-1.0.3.dist-info/top_level.txt
