Metadata-Version: 2.0
Name: tlsx
Version: 1.0.3
Summary: CLI tool for extracting TLS breakdown
Home-page: UNKNOWN
Author: Evyatar Meged
Author-email: evyatarmeged@gmail.com
License: UNKNOWN
Platform: UNKNOWN
Requires-Dist: pandas
Requires-Dist: click
